README.md
setup.py
adaxgboost/__init__.py
adaxgboost/axgboost_base.py
adaxgboost/axgboost_classifiers.py
adaxgboost/booster.py
axgb_online.egg-info/PKG-INFO
axgb_online.egg-info/SOURCES.txt
axgb_online.egg-info/dependency_links.txt
axgb_online.egg-info/requires.txt
axgb_online.egg-info/top_level.txt