Metadata-Version: 2.1
Name: axgb-online
Version: 0.1.11
Summary: ada-xgboost package
Home-page: UNKNOWN
License: UNKNOWN
Platform: UNKNOWN
